conversion/__init__.py
conversion/data_node.py
conversion/json_mapper.py
conversion/post_process.py
json2json-0.1.0.dist-info/LICENSE
json2json-0.1.0.dist-info/METADATA
json2json-0.1.0.dist-info/WHEEL
json2json-0.1.0.dist-info/top_level.txt
json2json-0.1.0.dist-info/RECORD
